pyllfea/__init__.py
pyllfea/two_dimensional/Plane_Stresss.py
pyllfea/two_dimensional/__init__.py
pyllfea-0.1.2.1.dist-info/LICENSE.txt
pyllfea-0.1.2.1.dist-info/METADATA
pyllfea-0.1.2.1.dist-info/WHEEL
pyllfea-0.1.2.1.dist-info/top_level.txt
pyllfea-0.1.2.1.dist-info/RECORD
